prim_batch/__init__.py
prim_batch/__main__.py
prim_batch-0.6.1.dist-info/entry_points.txt
prim_batch-0.6.1.dist-info/LICENSE
prim_batch-0.6.1.dist-info/METADATA
prim_batch-0.6.1.dist-info/WHEEL
prim_batch-0.6.1.dist-info/RECORD
