Metadata-Version: 2.1
Name: prim-batch
Version: 0.6.1
Summary: Primitive Batch - Multiplatform Python script for batch execution of prim-ctrl and prim-sync commands.
Home-page: https://github.com/lmagyar/prim-batch
License: Apache-2.0
Author: Laszlo Magyar
Author-email: lmagyar1973@gmail.com
Requires-Python: >=3.12,<4.0
Classifier: Development Status :: 4 - Beta
Classifier: Environment :: Console
Classifier: License :: OSI Approved :: Apache Software License
Classifier: Operating System :: OS Independent
Classifier: Programming Language :: Python :: 3
Classifier: Programming Language :: Python :: 3.12
Classifier: Programming Language :: Python :: 3.13
Requires-Dist: filelock (>=3.16.1,<4.0.0)
Project-URL: Change Log, https://github.com/lmagyar/prim-batch/blob/main/CHANGELOG.md
Project-URL: Repository, https://github.com/lmagyar/prim-batch
